{
  "T404DT":"https://dl.konkur.in/2025/07/Konkur1404-Tajrobi-Tir-%5Bwww.konkur.in%5D.pdf" ,
  "T404DO":"https://dl.konkur.in/2025/04/Konkur1404-Tajrobi-%5Bkonkur.in%5D.pdf" ,
  "T404KT":"https://dl.konkur.in/2025/07/Kharej1404-Tajrobi-%5Bwww.konkur.in%5D.pdf" ,
  "T404KO":"https://dl.alirezaafshar.org/konkur/1404/konkur-tajrobi-ordibehesht1404.pdf" ,
  "T403DT":"https://dl.konkur.in/2024/07/Konkur1403-Tajrobi-%5Bkonkur.in%5D.pdf" ,
  "T403DO":"https://dl.konkur.in/2024/04/Tajrobi1403-%5Bkonkur.in%5D.pdf" ,
  "T403KT":"https://dl.konkur.in/2024/07/Tajrobi-Kharej1403-%5Bkonkur.in%5D.pdf" ,
  "T403KO":"https://dl.alirezaafshar.org/konkur/1403/konkur-tajrobi-ordibehesht1403.pdf" ,
  "T402DT":"https://dl.konkur.in/2023/07/Kharej-Konkur1402-Tajrobi-%5Bkonkur.in%5D.pdf" ,
  "T402DD":"https://dl.konkur.in/2023/01/Tajrobi1402-%5Bwww.konkur.in%5D.pdf" ,
  "T402KT":"https://dl.konkur.in/2023/07/Kharej-Konkur1402-Tajrobi-%5Bkonkur.in%5D.pdf" ,
  "T401DT":"https://dl.konkur.in/2022/07/Konkur1401-Tajrobi-%5Bkonkur.in%5D.pdf" ,
  "T401KT":"https://dl.konkur.in/2022/06/Kharej-Konkur1401-Tajrobi-%5Bkonkur.in%5D.pdf" ,
  "T400DT":"https://dl.konkur.in/2021/07/Konkur1400-Tajrobi-%5Bkonkur.in%5D.pdf" ,
  "T400KT":"https://dl.konkur.in/2022/03/Kharej-Tajrobi1400-Soal-PasokhTashrihi-%5Bkonkur.in%5D.pdf" ,
  "T399DT":"https://dl.konkur.in/2020/08/Tajrobi99-J-%5Bkonkur.in%5D.pdf" ,
  "T399KT":"https://dl.konkur.in/2020/08/Kharej99-Tajrobi-J-%5Bkonkur.in%5D.pdf" ,
  "T398DT":"https://dl.konkur.in/2019/07/Konkur98-Tajrobi-NezamJadid-%5Bkonkur.in%5D.pdf" ,
  "T398KT":"https://dl.konkur.in/2019/07/Kharej-Konkur98-Tajrobi-NezamJadid-%5Bkonkur.in%5D.pdf" ,
  "T397DT":"https://dl.konkur.in/post/97/04/Tajrobi97-%5Bkonkur.in%5D.pdf" ,
  "T397KT":"https://dl.konkur.in/post/97/04/Tajrobi97-kharej-%5Bkonkur.in%5D.pdf" ,
  "T396DT":"https://file.gozine2.ir/Download/102192" ,
  "T396KT":"https://file.gozine2.ir/Download/102207" ,
  "T395DT":"https://file.gozine2.ir/Download/98194" ,
  "T395KT":"https://file.gozine2.ir/Download/98180"
}